[
  {
    "name": "Allswell Water Chestnut & Sugar Cane",
    "brand": null,
    "price_sgd": 2.54,
    "original_price_sgd": null,
    "discount_sgd": null,
    "unit": "1 L",
    "unified_category": "Beverages",
    "category_slug": "beverages",
    "store": "shengsiong",
    "product_url": "https://shengsiong.com.sg/product/allswell-water-chestnut-sugar-cane-1-l",
    "scraped_at": "2026-04-03T21:07:24.237701"
  },
  {
    "name": "Allswell Golden Pear With Aloe Vera",
    "brand": null,
    "price_sgd": 2.54,
    "original_price_sgd": null,
    "discount_sgd": null,
    "unit": "1 L",
    "unified_category": "Beverages",
    "category_slug": "beverages",
    "store": "shengsiong",
    "product_url": "https://shengsiong.com.sg/product/allswell-golden-pear-with-aloe-vera-1-l",
    "scraped_at": "2026-04-03T21:07:24.237701"
  },
  {
    "name": "Allswell Starfruit Replenish",
    "brand": null,
    "price_sgd": 2.54,
    "original_price_sgd": null,
    "discount_sgd": null,
    "unit": "1 L",
    "unified_category": "Beverages",
    "category_slug": "beverages",
    "store": "shengsiong",
    "product_url": "https://shengsiong.com.sg/product/allswell-starfruit-replenish-1-l",
    "scraped_at": "2026-04-03T21:07:24.237701"
  },
  {
    "name": "Authentic Tea House Oolong Chinese Tea Drink",
    "brand": null,
    "price_sgd": 2.1,
    "original_price_sgd": 2.35,
    "discount_sgd": 0.25,
    "unit": "1.5 L",
    "unified_category": "Beverages",
    "category_slug": "beverages",
    "store": "shengsiong",
    "product_url": "https://shengsiong.com.sg/product/authentic-tea-house-oolong-chinese-tea-drink-15-l",
    "scraped_at": "2026-04-03T21:07:24.237701"
  },
  {
    "name": "Authentic Tea House Ayataka Japanese Green Tea Drink",
    "brand": null,
    "price_sgd": 24.0,
    "original_price_sgd": 26.2,
    "discount_sgd": 2.2,
    "unit": "12 x 1.5 L",
    "unified_category": "Beverages",
    "category_slug": "beverages",
    "store": "shengsiong",
    "product_url": "https://shengsiong.com.sg/product/authentic-tea-house-ayataka-japanese-green-tea-drink-12-x-15-l",
    "scraped_at": "2026-04-03T21:07:24.237701"
  },
  {
    "name": "Authentic Tea House Ayataka Japanese Green Tea Drink",
    "brand": null,
    "price_sgd": 2.1,
    "original_price_sgd": 2.35,
    "discount_sgd": 0.25,
    "unit": "1.5 L",
    "unified_category": "Beverages",
    "category_slug": "beverages",
    "store": "shengsiong",
    "product_url": "https://shengsiong.com.sg/product/authentic-tea-house-ayataka-japanese-green-tea-drink-15-l",
    "scraped_at": "2026-04-03T21:07:24.237701"
  },
  {
    "name": "Authentic Tea House Oolong Chinese Tea Drink",
    "brand": null,
    "price_sgd": 24.0,
    "original_price_sgd": 26.2,
    "discount_sgd": 2.2,
    "unit": "12 x 1.5 L",
    "unified_category": "Beverages",
    "category_slug": "beverages",
    "store": "shengsiong",
    "product_url": "https://shengsiong.com.sg/product/authentic-tea-house-oolong-chinese-tea-drink-12-x-15-l",
    "scraped_at": "2026-04-03T21:07:24.237701"
  },
  {
    "name": "BUNDABERG Sarsaparilla",
    "brand": null,
    "price_sgd": 8.0,
    "original_price_sgd": 9.55,
    "discount_sgd": 1.55,
    "unit": "4 x 375 ml",
    "unified_category": "Beverages",
    "category_slug": "beverages",
    "store": "shengsiong",
    "product_url": "https://shengsiong.com.sg/product/bundaberg-sarsaparilla-4-x-375-ml",
    "scraped_at": "2026-04-03T21:07:24.237701"
  },
  {
    "name": "BUNDABERG Sarsaparilla",
    "brand": null,
    "price_sgd": 2.05,
    "original_price_sgd": 2.5,
    "discount_sgd": 0.45,
    "unit": "375 ml",
    "unified_category": "Beverages",
    "category_slug": "beverages",
    "store": "shengsiong",
    "product_url": "https://shengsiong.com.sg/product/bundaberg-sarsaparilla-375-ml",
    "scraped_at": "2026-04-03T21:07:24.237701"
  },
  {
    "name": "Cha Pai Lemon Red Tea",
    "brand": null,
    "price_sgd": 1.2,
    "original_price_sgd": 1.62,
    "discount_sgd": 0.42,
    "unit": "500 ml",
    "unified_category": "Beverages",
    "category_slug": "beverages",
    "store": "shengsiong",
    "product_url": "https://shengsiong.com.sg/product/cha-pai-lemon-red-tea-500-ml",
    "scraped_at": "2026-04-03T21:07:24.237701"
  },
  {
    "name": "Cha Pai Grapefruit Jasmine Tea",
    "brand": null,
    "price_sgd": 1.2,
    "original_price_sgd": 1.62,
    "discount_sgd": 0.42,
    "unit": "500 ml",
    "unified_category": "Beverages",
    "category_slug": "beverages",
    "store": "shengsiong",
    "product_url": "https://shengsiong.com.sg/product/cha-pai-grapefruit-jasmine-tea-500-ml",
    "scraped_at": "2026-04-03T21:07:24.237701"
  },
  {
    "name": "Cha Pai Pomelo Green Tea",
    "brand": null,
    "price_sgd": 1.2,
    "original_price_sgd": 1.62,
    "discount_sgd": 0.42,
    "unit": "500 ml",
    "unified_category": "Beverages",
    "category_slug": "beverages",
    "store": "shengsiong",
    "product_url": "https://shengsiong.com.sg/product/cha-pai-pomelo-green-tea-500-ml",
    "scraped_at": "2026-04-03T21:07:24.237701"
  },
  {
    "name": "Coca-Cola Original Taste",
    "brand": null,
    "price_sgd": 29.8,
    "original_price_sgd": 31.5,
    "discount_sgd": 1.7,
    "unit": "12 x 1.5 L",
    "unified_category": "Beverages",
    "category_slug": "beverages",
    "store": "shengsiong",
    "product_url": "https://shengsiong.com.sg/product/coca-cola-original-taste-12-x-15-l",
    "scraped_at": "2026-04-03T21:07:24.237701"
  },
  {
    "name": "F&N Flashy Fruitade",
    "brand": null,
    "price_sgd": 1.95,
    "original_price_sgd": 2.1,
    "discount_sgd": 0.15,
    "unit": "1.5 L",
    "unified_category": "Beverages",
    "category_slug": "beverages",
    "store": "shengsiong",
    "product_url": "https://shengsiong.com.sg/product/fn-flashy-fruitade-15-l",
    "scraped_at": "2026-04-03T21:07:24.237701"
  },
  {
    "name": "FUZE TEA Jasmine Flavoured Green Tea Drink",
    "brand": null,
    "price_sgd": 21.2,
    "original_price_sgd": 26.3,
    "discount_sgd": 5.1,
    "unit": "12 x 1.5 L",
    "unified_category": "Beverages",
    "category_slug": "beverages",
    "store": "shengsiong",
    "product_url": "https://shengsiong.com.sg/product/fuze-tea-jasmine-flavoured-green-tea-drink-12-x-15-l",
    "scraped_at": "2026-04-03T21:07:24.237701"
  },
  {
    "name": "FUZE TEA Jasmine Flavoured Green Tea Drink",
    "brand": null,
    "price_sgd": 1.85,
    "original_price_sgd": 2.25,
    "discount_sgd": 0.4,
    "unit": "1.5 L",
    "unified_category": "Beverages",
    "category_slug": "beverages",
    "store": "shengsiong",
    "product_url": "https://shengsiong.com.sg/product/fuze-tea-jasmine-flavoured-green-tea-drink-15-l",
    "scraped_at": "2026-04-03T21:07:24.237701"
  },
  {
    "name": "FUZE TEA Passionfruit Flavoured Tea Drink",
    "brand": null,
    "price_sgd": 1.85,
    "original_price_sgd": 2.25,
    "discount_sgd": 0.4,
    "unit": "1.5 L",
    "unified_category": "Beverages",
    "category_slug": "beverages",
    "store": "shengsiong",
    "product_url": "https://shengsiong.com.sg/product/fuze-tea-passionfruit-flavoured-tea-drink-15-l",
    "scraped_at": "2026-04-03T21:07:24.237701"
  },
  {
    "name": "FUZE TEA Mango Green Tea",
    "brand": null,
    "price_sgd": 15.2,
    "original_price_sgd": null,
    "discount_sgd": null,
    "unit": "12 x 500 ml",
    "unified_category": "Beverages",
    "category_slug": "beverages",
    "store": "shengsiong",
    "product_url": "https://shengsiong.com.sg/product/fuze-tea-mango-green-tea-12-x-500-ml",
    "scraped_at": "2026-04-03T21:07:24.237701"
  },
  {
    "name": "FUZE TEA Lychee And Rose Flavoured White Tea Drink",
    "brand": null,
    "price_sgd": 1.85,
    "original_price_sgd": 2.25,
    "discount_sgd": 0.4,
    "unit": "1.5 L",
    "unified_category": "Beverages",
    "category_slug": "beverages",
    "store": "shengsiong",
    "product_url": "https://shengsiong.com.sg/product/fuze-tea-lychee-and-rose-flavoured-white-tea-drink-15-l",
    "scraped_at": "2026-04-03T21:07:24.237701"
  }
]